CHANGELOG.md
syslogserver_to_cloudwatch/__main__.py
syslogserver_to_cloudwatch-0.1.2.dist-info/LICENSE
syslogserver_to_cloudwatch-0.1.2.dist-info/METADATA
syslogserver_to_cloudwatch-0.1.2.dist-info/WHEEL
syslogserver_to_cloudwatch-0.1.2.dist-info/RECORD
