Metadata-Version: 2.1
Name: syslogserver_to_cloudwatch
Version: 0.1.2
Summary: SysLog server that sends LogEvents to AWS Cloudwatch
Home-page: https://github.com/bulv1ne/syslogserver_to_cloudwatch
License: MIT
Author: Niels Lemmens
Author-email: 1936122+bulv1ne@users.noreply.github.com
Requires-Python: >=3.11,<4.0
Classifier: License :: OSI Approved :: MIT License
Classifier: Programming Language :: Python :: 3
Classifier: Programming Language :: Python :: 3.11
Classifier: Programming Language :: Python :: 3.12
Requires-Dist: boto3 (>=1.34)
Project-URL: Repository, https://github.com/bulv1ne/syslogserver_to_cloudwatch
